instpector/__init__.py
instpector/__main__.py
instpector/endpoint_factory.py
instpector/endpoints.py
instpector/instpector.py
instpector/apis/__init__.py
instpector/apis/exceptions.py
instpector/apis/http_request.py
instpector/apis/instagram/__init__.py
instpector/apis/instagram/authenticate.py
instpector/apis/instagram/base_api.py
instpector/apis/instagram/base_follow.py
instpector/apis/instagram/base_graph_ql.py
instpector/apis/instagram/comments.py
instpector/apis/instagram/definitions.py
instpector/apis/instagram/followers.py
instpector/apis/instagram/following.py
instpector/apis/instagram/like_graph_ql.py
instpector/apis/instagram/parser.py
instpector/apis/instagram/profile.py
instpector/apis/instagram/story.py
instpector/apis/instagram/story_reel.py
instpector/apis/instagram/timeline.py
instpector/apis/instagram/utilities.py
instpector-0.2.7.dist-info/LICENSE
instpector-0.2.7.dist-info/METADATA
instpector-0.2.7.dist-info/WHEEL
instpector-0.2.7.dist-info/top_level.txt
instpector-0.2.7.dist-info/RECORD
