Metadata-Version: 2.1
Name: instpector
Version: 0.2.7
Summary: A simple Instagram's web API library
Home-page: https://github.com/niuware/instpector
Author: Erik Lopez
License: UNKNOWN
Download-URL: https://github.com/niuware/instpector/archive/0.2.2.tar.gz
Keywords: instagram web-api instagram-client
Platform: UNKNOWN
Classifier: Programming Language :: Python :: 3
Classifier: License :: OSI Approved :: MIT License
Classifier: Operating System :: OS Independent
Requires-Dist: requests
